{
    "boss1": {
        "texture": "boss1",
        "health": 800,
        "bodyWidth": 48,
        "bodyHeight": 64,
        "gold": 500,
        "moveSpeed": 400,
        "damage": 100,
        "depth": 1
    },
    "amalia": {
        "texture": "Amalia",
        "health": 100,
        "bodyWidth": 48,
        "bodyHeight": 64,
        "gold": 40,
        "moveSpeed": 420,
        "damage": 100
    },
    "wellyYellow": {
        "texture": "player",
        "health": 200,
        "bodyWidth": 48,
        "bodyHeight": 64,
        "gold": 150,
        "moveSpeed": 480,
        "damage": 100
    },
    "wellyRed": {
        "texture": "wellyRed",
        "health": 160,
        "bodyWidth": 48,
        "bodyHeight": 64,
        "gold": 80,
        "moveSpeed": 490,
        "damage": 10
    },
    "wellyWhite": {
        "texture": "wellyWhite",
        "health": 100,
        "bodyWidth": 48,
        "bodyHeight": 64,
        "gold": 20,
        "moveSpeed": 100,
        "damage": 10
    },
    "wellyItaly": {
        "texture": "wellyItaly",
        "health": 100,
        "bodyWidth": 48,
        "bodyHeight": 64,
        "gold": 20,
        "moveSpeed": 100,
        "damage": 10
    }
}